roc/__init__.py
roc/dadi/__init__.py
roc/dadi/commands.py
roc/dadi/config/__init__.py
roc/dadi/constants.py
roc/dadi/descriptor.json
roc/dadi/exceptions.py
roc/dadi/tasks/__init__.py
roc/dadi/tasks/deliver_data.py
roc/dadi/tasks/feed_input.py
roc/dadi/tasks/publish_data.py
roc/dadi/tasks/share_output.py
roc/dadi/tests/__init__.py
roc/dadi/tests/data-tasks/test_deliver_data.yml
roc/dadi/tests/test_dadi.py
roc/dadi/tests/test_deliver_data.py
roc/dadi/tests/test_feed_input.py
roc/dadi/tests/test_publish_data.py
roc/dadi/tests/test_share_data.py
roc/dadi/tools/__init__.py
roc/dadi/tools/file_helper.py
roc/dadi/tools/time.py
roc_dadi-0.4.0.dist-info/LICENSE
roc_dadi-0.4.0.dist-info/METADATA
roc_dadi-0.4.0.dist-info/WHEEL
roc_dadi-0.4.0.dist-info/RECORD
